warcprox/__init__.py
warcprox/bigtable.py
warcprox/certauth.py
warcprox/controller.py
warcprox/crawl_log.py
warcprox/dedup.py
warcprox/main.py
warcprox/mime_type_filter.py
warcprox/mitmproxy.py
warcprox/playback.py
warcprox/ssl_util.py
warcprox/stats.py
warcprox/warc.py
warcprox/warcproxy.py
warcprox/writer.py
warcprox/writerthread.py
warcprox-2.11.0.dist-info/METADATA
warcprox-2.11.0.dist-info/WHEEL
warcprox-2.11.0.dist-info/entry_points.txt
warcprox-2.11.0.dist-info/top_level.txt
warcprox-2.11.0.dist-info/RECORD
