Metadata-Version: 2.4
Name: warcprox
Version: 2.11.0
Summary: WARC writing MITM HTTP/S proxy
Author-email: Noah Levitt <nlevitt@archive.org>
Maintainer-email: Vangelis Banos <vangelis@archive.org>, Adam Miller <adam@archive.org>, Barbara Miller <barbara@archive.org>, Alex Dempsey <avdempsey@archive.org>, Gretchen Leigh Miller <gmiller@archive.org>, Misty De Méo <misty@archive.org>
License-Expression: GPL-2.0-or-later
Project-URL: Homepage, https://github.com/internetarchive/warcprox
Project-URL: Issues, https://github.com/internetarchive/warcprox/issues
Classifier: Development Status :: 5 - Production/Stable
Classifier: Programming Language :: Python :: 3
Classifier: Programming Language :: Python :: 3.9
Classifier: Programming Language :: Python :: 3.10
Classifier: Programming Language :: Python :: 3.11
Classifier: Programming Language :: Python :: 3.12
Classifier: Programming Language :: Python :: 3.13
Classifier: Operating System :: OS Independent
Classifier: Environment :: Console
Classifier: Topic :: Internet :: Proxy Servers
Classifier: Topic :: Internet :: WWW/HTTP
Classifier: Topic :: Software Development :: Libraries :: Python Modules
Classifier: Topic :: System :: Archiving
Requires-Python: >=3.9
Requires-Dist: warctools>=5.0.0
Requires-Dist: urlcanon>=0.3.0
Requires-Dist: doublethink==0.4.9
Requires-Dist: urllib3>=1.23
Requires-Dist: requests>=2.0.1
Requires-Dist: PySocks>=1.6.8
Requires-Dist: cryptography<46,>=45
Requires-Dist: idna
Requires-Dist: PyYAML>=5.1
Requires-Dist: cachetools
Requires-Dist: rfc3986>=1.5.0
Requires-Dist: setuptools>=75.8.0; python_version >= "3.12"
Provides-Extra: trough
Requires-Dist: trough; extra == "trough"
Provides-Extra: sentry
Requires-Dist: sentry-sdk; extra == "sentry"
